vkmini/__init__.py
vkmini/api.py
vkmini/api.pyi
vkmini/exceptions.py
vkmini/group_longpoll.py
vkmini/keyboard.py
vkmini/method_groups.py
vkmini/py.typed
vkmini/request.py
vkmini/user_longpoll.py
vkmini/utils.py
vkmini/types/__init__.py
vkmini/types/methods.pyi
vkmini/types/objects.py
vkmini/types/responses.py
vkmini-5.199.0.post1.dist-info/licenses/LICENSE
vkmini-5.199.0.post1.dist-info/METADATA
vkmini-5.199.0.post1.dist-info/WHEEL
vkmini-5.199.0.post1.dist-info/top_level.txt
vkmini-5.199.0.post1.dist-info/RECORD
