Metadata-Version: 2.4
Name: vkmini
Version: 5.199.0.post1
Summary: VK API requests library
Author-email: Elchin Sarkarov <elchin751@gmail.com>
Project-URL: Homepage, https://github.com/Elchinchel/vkmini
Project-URL: Bug Tracker, https://github.com/Elchinchel/vkmini/issues
Classifier: Programming Language :: Python :: 3
Classifier: License :: OSI Approved :: MIT License
Classifier: Operating System :: OS Independent
Requires-Python: >=3.8
License-File: LICENSE
Requires-Dist: typing-extensions
Requires-Dist: aiohttp>=3.6.2
Dynamic: license-file
